check_install.py
cli.py
config.py
core/__init__.py
core/category_validator.py
core/dedup.py
core/inventory.py
core/manifest.py
core/metadata.py
core/mover.py
core/outputs.py
core/parser.py
core/summarizer.py
core/taxonomy.py
research_assistant_llm-0.2.0.dist-info/licenses/LICENSE
utils/__init__.py
utils/cache_manager.py
utils/gemini_client.py
utils/hash.py
utils/llm_provider.py
utils/rate_limiter.py
utils/text.py
research_assistant_llm-0.2.0.dist-info/METADATA
research_assistant_llm-0.2.0.dist-info/WHEEL
research_assistant_llm-0.2.0.dist-info/entry_points.txt
research_assistant_llm-0.2.0.dist-info/top_level.txt
research_assistant_llm-0.2.0.dist-info/RECORD
