Metadata-Version: 2.4
Name: research-assistant-llm
Version: 0.2.0
Summary: Intelligent research paper analysis pipeline with LLM-driven categorization
Author: Research Assistant Team
Author-email: Karim <rexmirak@users.noreply.github.com>
License: MIT
Project-URL: Homepage, https://github.com/rexmirak/research_assistant
Project-URL: Repository, https://github.com/rexmirak/research_assistant
Project-URL: Issues, https://github.com/rexmirak/research_assistant/issues
Keywords: research,papers,llm,pdf,analysis,categorization,ollama,gemini
Classifier: Development Status :: 4 - Beta
Classifier: Intended Audience :: Science/Research
Classifier: License :: OSI Approved :: MIT License
Classifier: Programming Language :: Python :: 3
Classifier: Programming Language :: Python :: 3.12
Classifier: Programming Language :: Python :: 3.13
Classifier: Topic :: Scientific/Engineering
Classifier: Topic :: Text Processing
Requires-Python: >=3.10
License-File: LICENSE
Requires-Dist: click>=8.1.0
Requires-Dist: pydantic>=2.0.0
Requires-Dist: pyyaml>=6.0
Requires-Dist: PyMuPDF>=1.23.0
Requires-Dist: pdfminer.six>=20221105
Requires-Dist: ocrmypdf>=15.0.0
Requires-Dist: requests>=2.31.0
Requires-Dist: habanero>=1.2.3
Requires-Dist: datasketch>=1.6.0
Requires-Dist: xxhash>=3.4.0
Requires-Dist: ollama>=0.1.0
Requires-Dist: google-generativeai>=0.3.0
Requires-Dist: numpy>=1.24.0
Requires-Dist: scikit-learn>=1.3.0
Requires-Dist: pandas>=2.0.0
Requires-Dist: openpyxl>=3.1.0
Requires-Dist: sqlalchemy>=2.0.0
Requires-Dist: filelock>=3.12.0
Requires-Dist: tqdm>=4.66.0
Requires-Dist: coloredlogs>=15.0
Requires-Dist: python-dotenv>=1.0.0
Provides-Extra: dev
Requires-Dist: pytest>=7.4.0; extra == "dev"
Requires-Dist: pytest-cov>=4.1.0; extra == "dev"
Requires-Dist: pytest-mock>=3.12.0; extra == "dev"
Requires-Dist: black>=23.0.0; extra == "dev"
Requires-Dist: flake8>=6.0.0; extra == "dev"
Requires-Dist: mypy>=1.5.0; extra == "dev"
Requires-Dist: isort>=5.12.0; extra == "dev"
Requires-Dist: types-PyYAML>=6.0.0; extra == "dev"
Requires-Dist: pip-audit>=2.0.0; extra == "dev"
Requires-Dist: bandit>=1.7.0; extra == "dev"
Dynamic: author
Dynamic: license-file
Dynamic: requires-python
